MANIFEST.in
README
setup.cfg
setup.py
bioplus/__init__.py
bioplus/fasta.py
bioplus/genometools.py
bioplus/motif.py
bioplus/peaktools.py
bioplus/seqtools.py
bioplus/sitefinder.py
bioplus/tabfile.py
bioplus/wrappers.py
bioplus/data/genomes.db
scripts/align.py
scripts/align2.py
scripts/align_bwa.py
scripts/analyze.py
scripts/call_peaks.py
scripts/preprocess_reads.py
scripts/subtract_bam.py
seriesoftubes/__init__.py
seriesoftubes/bedgraph.py
seriesoftubes/cPreprocess.c
seriesoftubes/cPreprocess.pyx
seriesoftubes.egg-info/PKG-INFO
seriesoftubes.egg-info/SOURCES.txt
seriesoftubes.egg-info/dependency_links.txt
seriesoftubes.egg-info/requires.txt
seriesoftubes.egg-info/top_level.txt
seriesoftubes/converters/__init__.py
seriesoftubes/converters/anytotab.py
seriesoftubes/converters/bamtofastq.py
seriesoftubes/converters/bamtofastq2.py
seriesoftubes/converters/bamtotab.py
seriesoftubes/converters/cat.py
seriesoftubes/converters/discover.py
seriesoftubes/converters/fastqtotab.py
seriesoftubes/fnparsers/__init__.py
seriesoftubes/fnparsers/aligned.py
seriesoftubes/fnparsers/bowtie.py
seriesoftubes/fnparsers/illumina.py
seriesoftubes/fnparsers/peaks.py
seriesoftubes/tubes/__init__.py
seriesoftubes/tubes/polledpipe.py