Metadata-Version: 1.1
Name: seriesoftubes
Version: 0.9.6.9
Summary: An extended pipeline for Solexa ChIP-seq data
Home-page: https://github.com/benjschiller/seriesoftubes
Author: Benjamin Schiller
Author-email: benjamin.schiller@ucsf.edu
License: UNKNOWN
Platform: UNKNOWN
Classifier: Development Status :: 3 - Alpha
Classifier: License :: OSI Approved :: Artistic License
Classifier: Intended Audience :: Developers
Classifier: Intended Audience :: End Users/Desktop
Classifier: Intended Audience :: Science/Research
Classifier: Operating System :: MacOS :: MacOS X
Classifier: Operating System :: POSIX
Classifier: Programming Language :: Python :: 2.7
Classifier: Topic :: Scientific/Engineering :: Bio-Informatics
